langlearncopilot/__init__.py
langlearncopilot/datatypes.py
langlearncopilot/generators/__init__.py
langlearncopilot/generators/configs/prompts.yml
langlearncopilot/generators/main.py
langlearncopilot/generators/utils.py
langlearncopilot/llm_calls/__init__.py
langlearncopilot/llm_calls/llama2_call.py
langlearncopilot/llm_calls/openai_call.py
langlearncopilot/llm_calls/set_credentials.py
langlearncopilot/parsers/__init__.py
langlearncopilot/parsers/llm_phrase_parser.py
langlearncopilot/parsers/site_parser.py
langlearncopilot/parsers/tests/__init__.py
langlearncopilot/parsers/tests/test_site_parser.py
langlearncopilot/utilities/__init__.py
langlearncopilot/utilities/save_anki_format.py
langlearncopilot/utilities/tests/__init__.py
langlearncopilot/utilities/tests/test_save_anki_format.py
langlearncopilot-0.3.1.dist-info/LICENSE
langlearncopilot-0.3.1.dist-info/METADATA
langlearncopilot-0.3.1.dist-info/WHEEL
langlearncopilot-0.3.1.dist-info/RECORD
