Metadata-Version: 2.1
Name: langlearncopilot
Version: 0.3.1
Summary: LangLearnCopilot is a library to help you learn a 'human' language.
Home-page: https://github.com/osm3000/LangLearnCopilot
Keywords: langlearncopilot,gpt,copilot
Author: osm3000
Author-email: bd2fc312-d8c3-482f-8535-94c14174bc88@anonaddy.me
Requires-Python: >=3.9,<4.0
Classifier: License :: OSI Approved :: MIT License
Classifier: Programming Language :: Python :: 3
Classifier: Programming Language :: Python :: 3.9
Classifier: Programming Language :: Python :: 3.10
Classifier: Programming Language :: Python :: 3.11
Classifier: Topic :: Education
Classifier: Topic :: Scientific/Engineering :: Artificial Intelligence
Requires-Dist: beautifulsoup4 (>=4.12.2,<5.0.0)
Requires-Dist: openai (>=0.27.8,<0.28.0)
Requires-Dist: python-dotenv (>=1.0.0,<2.0.0)
Requires-Dist: pyyaml (>=6.0.1,<7.0.0)
Requires-Dist: requests (>=2.31.0,<3.0.0)
Project-URL: Bug Tracker, https://github.com/osm3000/LangLearnCopilot/issues
Project-URL: Home Page, https://github.com/osm3000/LangLearnCopilot
Project-URL: Repository, https://github.com/osm3000/LangLearnCopilot
